pipecat_ai_mcp_server-0.0.9.dist-info/licenses/LICENSE
pipecat_mcp_server/agent.py
pipecat_mcp_server/agent_ipc.py
pipecat_mcp_server/bot.py
pipecat_mcp_server/server.py
pipecat_mcp_server/processors/__init__.py
pipecat_mcp_server/processors/kokoro_tts.py
pipecat_mcp_server/processors/screen_capture/__init__.py
pipecat_mcp_server/processors/screen_capture/base_capture_backend.py
pipecat_mcp_server/processors/screen_capture/linux_x11_capture_backend.py
pipecat_mcp_server/processors/screen_capture/macos_capture_backend.py
pipecat_mcp_server/processors/screen_capture/screen_capture_processor.py
pipecat_ai_mcp_server-0.0.9.dist-info/METADATA
pipecat_ai_mcp_server-0.0.9.dist-info/WHEEL
pipecat_ai_mcp_server-0.0.9.dist-info/entry_points.txt
pipecat_ai_mcp_server-0.0.9.dist-info/top_level.txt
pipecat_ai_mcp_server-0.0.9.dist-info/RECORD
