Metadata-Version: 2.4
Name: pipecat-ai-mcp-server
Version: 0.0.9
Summary: Pipecat MCP server for your AI agents
License-Expression: BSD-2-Clause
Project-URL: Homepage, https://pipecat.ai
Project-URL: Documentation, https://docs.pipecat.ai/
Project-URL: Source, https://github.com/pipecat-ai/pipecat-mcp-server
Project-URL: Issues, https://github.com/pipecat-ai/pipecat-mcp-server/issues
Project-URL: Changelog, https://github.com/pipecat-ai/pipecat-mcp-server/blob/main/CHANGELOG.md
Keywords: pipecat,mcp,voice,ai,assistant,speech
Classifier: Development Status :: 5 - Production/Stable
Classifier: Intended Audience :: Developers
Classifier: Topic :: Communications :: Conferencing
Classifier: Topic :: Multimedia :: Sound/Audio
Classifier: Topic :: Multimedia :: Video
Classifier: Topic :: Scientific/Engineering :: Artificial Intelligence
Requires-Python: >=3.10
License-File: LICENSE
Requires-Dist: kokoro-onnx<1,>=0.5.0
Requires-Dist: loguru<1,>=0.7.0
Requires-Dist: mcp>=1.0.0
Requires-Dist: pip>=25.3
Requires-Dist: pipecat-ai[cartesia,deepgram,local-smart-turn-v3,rnnoise,runner,silero,webrtc,websocket]>=0.0.101
Requires-Dist: pipecat-ai[mlx-whisper]>=0.0.100; sys_platform == "darwin"
Requires-Dist: pipecat-ai[whisper]>=0.0.100; sys_platform != "darwin"
Requires-Dist: python-dotenv<2,>=1.0.0
Requires-Dist: requests<3,>=2.32.5
Provides-Extra: daily
Requires-Dist: daily-python~=0.23.0; extra == "daily"
Provides-Extra: screen
Requires-Dist: pyobjc-framework-ScreenCaptureKit>=11.0; sys_platform == "darwin" and extra == "screen"
Requires-Dist: pyobjc-framework-Quartz>=11.0; sys_platform == "darwin" and extra == "screen"
Requires-Dist: pyobjc-framework-CoreMedia>=11.0; sys_platform == "darwin" and extra == "screen"
Requires-Dist: python-xlib>=0.33; sys_platform == "linux" and extra == "screen"
Dynamic: license-file
